openpost/__init__.py
openpost-0.3.dist-info/LICENSE
openpost-0.3.dist-info/METADATA
openpost-0.3.dist-info/WHEEL
openpost-0.3.dist-info/top_level.txt
openpost-0.3.dist-info/RECORD
