Metadata-Version: 2.1
Name: openpost
Version: 0.3
Summary: A module to help prepare and execute html POST requests.
Home-page: https://github.com/rdswift/OpenPost
Author: Bob Swift
Author-email: bswift@rsds.ca
License: MIT
Download-URL: https://github.com/rdswift/OpenPost
Platform: any
Classifier: Intended Audience :: Developers
Classifier: License :: OSI Approved :: MIT License
Classifier: Operating System :: OS Independent
Classifier: Programming Language :: Python :: 3
Classifier: Topic :: Internet :: WWW/HTTP
